{
    "runNum": "0002154", 
    "0025001b4853500520353041": {
        "channel": "1", 
        "voltage": 2720, 
        "threshold": 1422, 
        "temperature": 22.56800000000004, 
        "temp_K": 295.718, 
        "good_adcfit": true, 
        "adcfit_results": {
            "fit_iter": 3, 
            "chi2": 0.663054466710364, 
            "N": 492.67899741581095, 
            "tau": 250.95011971221177, 
            "M": 133.74061780521544, 
            "mean": 1176.3628796062242, 
            "mean_err": 5.409399793671242, 
            "sig": 207.89589275937595, 
            "out_of_bounds": false, 
            "adcPerMIP": 944.9495462728909, 
            "adcPerMIP_err": 5.409399793671242
        }, 
        "bad_adcfit_reasons": [], 
        "pedestal": 231.41333333333333, 
        "thresh": 139.58666666666667, 
        "adcPerMIP": 945.8651270987349, 
        "good_pefit": true, 
        "pefit_results": {
            "fit_iter": 3, 
            "chi2": 0.0032943050814299916, 
            "N": 2.356232062081649, 
            "tau": 253.708549162402, 
            "M": 0.6536538374286693, 
            "mean": 1177.2784604320682, 
            "mean_err": 5.388693699623169, 
            "sig": 207.4200934883081, 
            "out_of_bounds": false, 
            "adcPerMIP": 945.8651270987349, 
            "adcPerMIP_err": 5.388693699623169, 
            "pePerMIP": 44.42629430888154, 
            "pePerMIP_err": 0.2531012988862255
        }, 
        "bad_pefit_reasons": [], 
        "gain": 21.290659997938228, 
        "good_gain": true, 
        "bad_gain_reasons": [], 
        "pePerMIP": 44.42629430888154
    }, 
    "0033000b4853500720353041": {
        "channel": "2", 
        "voltage": 2720, 
        "threshold": 1428, 
        "temperature": 23.38100000000003, 
        "temp_K": 296.531, 
        "good_adcfit": false, 
        "adcfit_results": {
            "fit_iter": 21, 
            "chi2": 222.32835675682202, 
            "N": 28899.999999999945, 
            "tau": 79.79052600014666, 
            "M": 133.71055802751698, 
            "mean": 608.8114563997847, 
            "mean_err": 257.3380688256816, 
            "sig": 138.28137518363422, 
            "out_of_bounds": true, 
            "adcPerMIP": 347.6083313997847, 
            "adcPerMIP_err": 257.3380688256816
        }, 
        "bad_adcfit_reasons": [
            "exceeded 20 fit iterations", 
            "opt[0] at upper bound", 
            "large chi2 of 222.3"
        ], 
        "pedestal": 261.203125, 
        "thresh": 120.796875, 
        "adcPerMIP": 1059.1816908634664, 
        "good_pefit": true, 
        "pefit_results": {
            "fit_iter": 3, 
            "chi2": 0.001769670312275699, 
            "N": 1.4101976515633594, 
            "tau": 292.62785192675864, 
            "M": 0.37298955804901107, 
            "mean": 1320.3848158634664, 
            "mean_err": 6.974443519390464, 
            "sig": 236.7404409597636, 
            "out_of_bounds": false, 
            "adcPerMIP": 1059.1816908634664, 
            "adcPerMIP_err": 6.974443519390464, 
            "pePerMIP": 46.72557995104737, 
            "pePerMIP_err": 0.3076761249655621
        }, 
        "bad_pefit_reasons": [], 
        "gain": 22.668133642709865, 
        "good_gain": true, 
        "bad_gain_reasons": [], 
        "pePerMIP": 46.72557995104737
    }, 
    "0025000f4853500520353041": {
        "channel": "3", 
        "voltage": 2720, 
        "threshold": 1422, 
        "temperature": 23.44300000000004, 
        "temp_K": 296.593, 
        "good_adcfit": true, 
        "adcfit_results": {
            "fit_iter": 7, 
            "chi2": 0.8833249216166634, 
            "N": 303.07058688107224, 
            "tau": 327.23945564124546, 
            "M": 99.15790388035845, 
            "mean": 1331.6975718217248, 
            "mean_err": 7.151508652836642, 
            "sig": 239.9254371124128, 
            "out_of_bounds": false, 
            "adcPerMIP": 1099.1164907406437, 
            "adcPerMIP_err": 7.151508652836642
        }, 
        "bad_adcfit_reasons": [], 
        "pedestal": 232.5810810810811, 
        "thresh": 151.4189189189189, 
        "adcPerMIP": 1096.869406422512, 
        "good_pefit": true, 
        "pefit_results": {
            "fit_iter": 2, 
            "chi2": 0.005052631885400209, 
            "N": 1.8454245051765261, 
            "tau": 320.4174947181187, 
            "M": 0.5846772988453585, 
            "mean": 1329.450487503593, 
            "mean_err": 7.182248670506613, 
            "sig": 240.84638346672634, 
            "out_of_bounds": false, 
            "adcPerMIP": 1096.869406422512, 
            "adcPerMIP_err": 7.182248670506613, 
            "pePerMIP": 47.7239025046899, 
            "pePerMIP_err": 0.31249384230128113
        }, 
        "bad_pefit_reasons": [], 
        "gain": 22.98364863004908, 
        "good_gain": true, 
        "bad_gain_reasons": [], 
        "pePerMIP": 47.7239025046899
    }, 
    "002100384853500520353041": {
        "channel": "4", 
        "voltage": 2720, 
        "threshold": 1424, 
        "temperature": 23.13100000000003, 
        "temp_K": 296.281, 
        "good_adcfit": true, 
        "adcfit_results": {
            "fit_iter": 7, 
            "chi2": 0.5929350915964228, 
            "N": 509.71663441853656, 
            "tau": 281.88775523854366, 
            "M": 106.43831136415845, 
            "mean": 1298.9555644209945, 
            "mean_err": 7.628225470577918, 
            "sig": 224.82955916822343, 
            "out_of_bounds": false, 
            "adcPerMIP": 986.2127072781374, 
            "adcPerMIP_err": 7.628225470577918
        }, 
        "bad_adcfit_reasons": [], 
        "pedestal": 312.74285714285713, 
        "thresh": 102.25714285714287, 
        "adcPerMIP": 985.9994113045935, 
        "good_pefit": true, 
        "pefit_results": {
            "fit_iter": 2, 
            "chi2": 0.0020201392734710564, 
            "N": 1.7744054019716635, 
            "tau": 280.65296719836016, 
            "M": 0.36743252916942803, 
            "mean": 1298.7422684474507, 
            "mean_err": 7.779218922126539, 
            "sig": 225.56394019750923, 
            "out_of_bounds": false, 
            "adcPerMIP": 985.9994113045935, 
            "adcPerMIP_err": 7.779218922126539, 
            "pePerMIP": 46.25499947328039, 
            "pePerMIP_err": 0.364937101401918
        }, 
        "bad_pefit_reasons": [], 
        "gain": 21.31660193562784, 
        "good_gain": true, 
        "bad_gain_reasons": [], 
        "pePerMIP": 46.25499947328039
    }, 
    "0025000c4853500520353041": {
        "channel": "5", 
        "voltage": 2720, 
        "threshold": 1424, 
        "temperature": 23.13100000000003, 
        "temp_K": 296.281, 
        "good_adcfit": true, 
        "adcfit_results": {
            "fit_iter": 7, 
            "chi2": 0.45323810383612984, 
            "N": 667.8598434862705, 
            "tau": 246.59875334127042, 
            "M": 109.52787965766227, 
            "mean": 1237.1482212665271, 
            "mean_err": 7.177559710042767, 
            "sig": 225.38775533517645, 
            "out_of_bounds": false, 
            "adcPerMIP": 972.040113158419, 
            "adcPerMIP_err": 7.177559710042767
        }, 
        "bad_adcfit_reasons": [], 
        "pedestal": 265.1081081081081, 
        "thresh": 118.89189189189187, 
        "adcPerMIP": 972.0144744618392, 
        "good_pefit": true, 
        "pefit_results": {
            "fit_iter": 3, 
            "chi2": 0.0012274440235115992, 
            "N": 1.8167817627270146, 
            "tau": 246.4841885182801, 
            "M": 0.29765765945765377, 
            "mean": 1237.1225825699473, 
            "mean_err": 7.210833406485448, 
            "sig": 225.4767899585792, 
            "out_of_bounds": false, 
            "adcPerMIP": 972.0144744618392, 
            "adcPerMIP_err": 7.210833406485448, 
            "pePerMIP": 44.64684907572264, 
            "pePerMIP_err": 0.331210078931982
        }, 
        "bad_pefit_reasons": [], 
        "gain": 21.77117746457915, 
        "good_gain": true, 
        "bad_gain_reasons": [], 
        "pePerMIP": 44.64684907572264
    }, 
    "002400084853500520353041": {
        "channel": "6", 
        "voltage": 2720, 
        "threshold": 1424, 
        "temperature": 23.31800000000004, 
        "temp_K": 296.468, 
        "good_adcfit": false, 
        "adcfit_results": {
            "fit_iter": 1, 
            "chi2": 22299052.66578521, 
            "N": 41699.99999735218, 
            "tau": 84.5853867877439, 
            "M": 10.000000017046709, 
            "mean": 416.00000000000006, 
            "mean_err": 120049.12821732566, 
            "sig": 50.0000000000261, 
            "out_of_bounds": true, 
            "adcPerMIP": 148.60000000000008, 
            "adcPerMIP_err": 120049.12821732566
        }, 
        "bad_adcfit_reasons": [
            "opt[0] at upper bound", 
            "opt[2] at lower bound", 
            "opt[3] at lower bound", 
            "opt[4] at lower bound", 
            "large chi2 of 22299052.7"
        ], 
        "pedestal": 267.4, 
        "thresh": 122.60000000000002, 
        "adcPerMIP": 1022.3811149320762, 
        "good_pefit": true, 
        "pefit_results": {
            "fit_iter": 3, 
            "chi2": 0.0008329678700127575, 
            "N": 1.5315569923398036, 
            "tau": 260.1424778396298, 
            "M": 0.24856857452074696, 
            "mean": 1289.7811149320762, 
            "mean_err": 7.191644225076673, 
            "sig": 233.11292510772026, 
            "out_of_bounds": false, 
            "adcPerMIP": 1022.3811149320762, 
            "adcPerMIP_err": 7.191644225076673, 
            "pePerMIP": 45.254236115857104, 
            "pePerMIP_err": 0.31832783398437675
        }, 
        "bad_pefit_reasons": [], 
        "gain": 22.591942825300137, 
        "good_gain": true, 
        "bad_gain_reasons": [], 
        "pePerMIP": 45.254236115857104
    }, 
    "002500104853500520353041": {
        "channel": "7", 
        "voltage": 2720, 
        "threshold": 1435, 
        "temperature": 22.81800000000004, 
        "temp_K": 295.968, 
        "good_adcfit": false, 
        "adcfit_results": {
            "fit_iter": 21, 
            "chi2": 113.81794232235288, 
            "N": 36599.99999999999, 
            "tau": 91.81874636491781, 
            "M": 145.10570907843078, 
            "mean": 742.7830909572722, 
            "mean_err": 42.30185301163804, 
            "sig": 135.7998932268574, 
            "out_of_bounds": true, 
            "adcPerMIP": 425.3215524957337, 
            "adcPerMIP_err": 42.30185301163804
        }, 
        "bad_adcfit_reasons": [
            "exceeded 20 fit iterations", 
            "opt[0] at upper bound", 
            "large chi2 of 113.8"
        ], 
        "pedestal": 317.46153846153845, 
        "thresh": 108.53846153846155, 
        "adcPerMIP": 1054.046853089404, 
        "good_pefit": true, 
        "pefit_results": {
            "fit_iter": 3, 
            "chi2": 0.0011135838574091376, 
            "N": 1.9638639433740277, 
            "tau": 274.99496644401034, 
            "M": 0.26834888330293055, 
            "mean": 1371.5083915509426, 
            "mean_err": 7.761676727963477, 
            "sig": 238.91242755210996, 
            "out_of_bounds": false, 
            "adcPerMIP": 1054.046853089404, 
            "adcPerMIP_err": 7.761676727963477, 
            "pePerMIP": 46.21189626264773, 
            "pePerMIP_err": 0.34029018608191974
        }, 
        "bad_pefit_reasons": [], 
        "gain": 22.80899375127724, 
        "good_gain": true, 
        "bad_gain_reasons": [], 
        "pePerMIP": 46.21189626264773
    }, 
    "0025001c4853500520353041": {
        "channel": "8", 
        "voltage": 2720, 
        "threshold": 1428, 
        "temperature": 22.69300000000004, 
        "temp_K": 295.843, 
        "good_adcfit": false, 
        "adcfit_results": {
            "fit_iter": 21, 
            "chi2": 62.95750091497792, 
            "N": 15612.138835389364, 
            "tau": 89.22267120814874, 
            "M": 245.2661654806783, 
            "mean": 397.0153724541125, 
            "mean_err": 55083.74778859639, 
            "sig": 165.94741165565702, 
            "out_of_bounds": true, 
            "adcPerMIP": 124.19345464589333, 
            "adcPerMIP_err": 55083.74778859639
        }, 
        "bad_adcfit_reasons": [
            "exceeded 20 fit iterations", 
            "opt[3] at lower bound", 
            "large chi2 of 63.0"
        ], 
        "pedestal": 272.82191780821915, 
        "thresh": 117.17808219178085, 
        "adcPerMIP": 982.7241862180041, 
        "good_pefit": true, 
        "pefit_results": {
            "fit_iter": 3, 
            "chi2": 0.002767728445623947, 
            "N": 2.067236254005119, 
            "tau": 272.41109280089836, 
            "M": 0.33165520974758533, 
            "mean": 1255.5461040262232, 
            "mean_err": 8.038111658548527, 
            "sig": 216.66713931029923, 
            "out_of_bounds": false, 
            "adcPerMIP": 982.7241862180041, 
            "adcPerMIP_err": 8.038111658548527, 
            "pePerMIP": 46.12195115592319, 
            "pePerMIP_err": 0.3772507062517638
        }, 
        "bad_pefit_reasons": [], 
        "gain": 21.307081803537233, 
        "good_gain": true, 
        "bad_gain_reasons": [], 
        "pePerMIP": 46.12195115592319
    }
}