{
    "runNum": "0002201", 
    "0025001b4853500520353041": {
        "channel": "1", 
        "voltage": 2520, 
        "threshold": 1362, 
        "temperature": -37.74399999999997, 
        "temp_K": 235.406, 
        "good_adcfit": false, 
        "adcfit_results": {
            "fit_iter": 21, 
            "chi2": 9899.36408295267, 
            "N": 45099.99999999999, 
            "tau": 61.56212478131945, 
            "M": 182.64132877855383, 
            "mean": 462.4345192714627, 
            "mean_err": 193.08705884273147, 
            "sig": 74.50726806531578, 
            "out_of_bounds": true, 
            "adcPerMIP": 249.77905708658875, 
            "adcPerMIP_err": 193.08705884273147
        }, 
        "bad_adcfit_reasons": [
            "exceeded 20 fit iterations", 
            "opt[0] at upper bound", 
            "large chi2 of 9899.4"
        ], 
        "pedestal": 212.65546218487395, 
        "thresh": 79.34453781512605, 
        "adcPerMIP": 967.4679363824827, 
        "good_pefit": true, 
        "pefit_results": {
            "fit_iter": 2, 
            "chi2": 0.0012760401153237707, 
            "N": 0.8107904022928275, 
            "tau": 279.9094128009581, 
            "M": 0.2799608099918968, 
            "mean": 1180.1233985673566, 
            "mean_err": 6.2597878896527055, 
            "sig": 209.6558381979458, 
            "out_of_bounds": false, 
            "adcPerMIP": 967.4679363824827, 
            "adcPerMIP_err": 6.2597878896527055, 
            "pePerMIP": 44.965175856075575, 
            "pePerMIP_err": 0.29093725248656477
        }, 
        "bad_pefit_reasons": [], 
        "gain": 21.51593801121009, 
        "good_gain": true, 
        "bad_gain_reasons": [], 
        "pePerMIP": 44.965175856075575
    }, 
    "0033000b4853500720353041": {
        "channel": "2", 
        "voltage": 2520, 
        "threshold": 1368, 
        "temperature": -36.86899999999997, 
        "temp_K": 236.281, 
        "good_adcfit": true, 
        "adcfit_results": {
            "fit_iter": 4, 
            "chi2": 0.7990975778074403, 
            "N": 474.6907643278771, 
            "tau": 258.71231257771046, 
            "M": 111.2913862746223, 
            "mean": 1281.9088068120516, 
            "mean_err": 8.996869616467505, 
            "sig": 242.00180480588085, 
            "out_of_bounds": false, 
            "adcPerMIP": 1035.3657033637758, 
            "adcPerMIP_err": 8.996869616467505
        }, 
        "bad_adcfit_reasons": [], 
        "pedestal": 246.54310344827587, 
        "thresh": 61.45689655172413, 
        "adcPerMIP": 1062.1300663627883, 
        "good_pefit": true, 
        "pefit_results": {
            "fit_iter": 2, 
            "chi2": 0.000730910111377514, 
            "N": 0.28017277852083144, 
            "tau": 328.5330519436732, 
            "M": 0.10085051334560789, 
            "mean": 1308.673169811064, 
            "mean_err": 8.80161101592301, 
            "sig": 236.44225906937638, 
            "out_of_bounds": false, 
            "adcPerMIP": 1062.1300663627883, 
            "adcPerMIP_err": 8.80161101592301, 
            "pePerMIP": 47.12834479992188, 
            "pePerMIP_err": 0.3905410193063178
        }, 
        "bad_pefit_reasons": [], 
        "gain": 22.536969436799506, 
        "good_gain": true, 
        "bad_gain_reasons": [], 
        "pePerMIP": 47.12834479992188
    }, 
    "0025000f4853500520353041": {
        "channel": "3", 
        "voltage": 2520, 
        "threshold": 1362, 
        "temperature": -36.74399999999997, 
        "temp_K": 236.406, 
        "good_adcfit": false, 
        "adcfit_results": {
            "fit_iter": 11, 
            "chi2": 288.72199041634127, 
            "N": 43699.99999999711, 
            "tau": 62.73598727782334, 
            "M": 192.54290784848914, 
            "mean": 463.4128680211638, 
            "mean_err": 1136.6934832723, 
            "sig": 125.82916257939388, 
            "out_of_bounds": true, 
            "adcPerMIP": 239.38765793713017, 
            "adcPerMIP_err": 1136.6934832723
        }, 
        "bad_adcfit_reasons": [
            "opt[0] at upper bound", 
            "large chi2 of 288.7"
        ], 
        "pedestal": 224.0252100840336, 
        "thresh": 84.9747899159664, 
        "adcPerMIP": 1104.73398934684, 
        "good_pefit": true, 
        "pefit_results": {
            "fit_iter": 2, 
            "chi2": 0.001364110984831185, 
            "N": 0.6976335981296509, 
            "tau": 316.440456874275, 
            "M": 0.22353436791608272, 
            "mean": 1328.7591994308737, 
            "mean_err": 8.403583324654413, 
            "sig": 243.89780316205633, 
            "out_of_bounds": false, 
            "adcPerMIP": 1104.73398934684, 
            "adcPerMIP_err": 8.403583324654413, 
            "pePerMIP": 48.20561826310512, 
            "pePerMIP_err": 0.36669454701035914
        }, 
        "bad_pefit_reasons": [], 
        "gain": 22.917121056662484, 
        "good_gain": true, 
        "bad_gain_reasons": [], 
        "pePerMIP": 48.20561826310512
    }, 
    "002100384853500520353041": {
        "channel": "4", 
        "voltage": 2520, 
        "threshold": 1364, 
        "temperature": -36.86899999999997, 
        "temp_K": 236.281, 
        "good_adcfit": true, 
        "adcfit_results": {
            "fit_iter": 6, 
            "chi2": 0.9133100033300078, 
            "N": 607.2872373059004, 
            "tau": 244.58861141405887, 
            "M": 119.03179080818559, 
            "mean": 1172.7477821846944, 
            "mean_err": 8.338356882885385, 
            "sig": 203.76583220928407, 
            "out_of_bounds": false, 
            "adcPerMIP": 895.1548618307121, 
            "adcPerMIP_err": 8.338356882885385
        }, 
        "bad_adcfit_reasons": [], 
        "pedestal": 277.5929203539823, 
        "thresh": 54.40707964601768, 
        "adcPerMIP": 895.1549754912302, 
        "good_pefit": true, 
        "pefit_results": {
            "fit_iter": 6, 
            "chi2": 0.0012128951694868346, 
            "N": 0.8064888898530864, 
            "tau": 244.58880748472586, 
            "M": 0.15807670892489462, 
            "mean": 1172.7478958452125, 
            "mean_err": 8.338349929283348, 
            "sig": 203.765775083832, 
            "out_of_bounds": false, 
            "adcPerMIP": 895.1549754912302, 
            "adcPerMIP_err": 8.338349929283348, 
            "pePerMIP": 44.74503442800187, 
            "pePerMIP_err": 0.4167990625911073
        }, 
        "bad_pefit_reasons": [], 
        "gain": 20.005683020125996, 
        "good_gain": true, 
        "bad_gain_reasons": [], 
        "pePerMIP": 44.74503442800187
    }, 
    "0025000c4853500520353041": {
        "channel": "5", 
        "voltage": 2520, 
        "threshold": 1364, 
        "temperature": -36.80699999999999, 
        "temp_K": 236.343, 
        "good_adcfit": false, 
        "adcfit_results": {
            "fit_iter": 1, 
            "chi2": 226.34732433169327, 
            "N": 64999.99999999928, 
            "tau": 64.01017823000785, 
            "M": 10.000000000000002, 
            "mean": 328.00000000000006, 
            "mean_err": 1175987167.7284174, 
            "sig": 999.9999999999999, 
            "out_of_bounds": true, 
            "adcPerMIP": 75.80672268907568, 
            "adcPerMIP_err": 1175987167.7284174
        }, 
        "bad_adcfit_reasons": [
            "opt[0] at upper bound", 
            "opt[2] at lower bound", 
            "opt[3] at lower bound", 
            "opt[4] at upper bound", 
            "large chi2 of 226.3"
        ], 
        "pedestal": 252.19327731092437, 
        "thresh": 71.80672268907563, 
        "adcPerMIP": 850.3089828728163, 
        "good_pefit": true, 
        "pefit_results": {
            "fit_iter": 2, 
            "chi2": 0.0010539949707176464, 
            "N": 1.2288861494153565, 
            "tau": 211.63295121556828, 
            "M": 0.18735824298392945, 
            "mean": 1102.5022601837406, 
            "mean_err": 9.185215985332743, 
            "sig": 207.5911462356708, 
            "out_of_bounds": false, 
            "adcPerMIP": 850.3089828728163, 
            "adcPerMIP_err": 9.185215985332743, 
            "pePerMIP": 42.38946468223126, 
            "pePerMIP_err": 0.4578998886892457
        }, 
        "bad_pefit_reasons": [], 
        "gain": 20.059441402411654, 
        "good_gain": true, 
        "bad_gain_reasons": [], 
        "pePerMIP": 42.38946468223126
    }, 
    "002400084853500520353041": {
        "channel": "6", 
        "voltage": 2520, 
        "threshold": 1364, 
        "temperature": -36.36899999999997, 
        "temp_K": 236.781, 
        "good_adcfit": true, 
        "adcfit_results": {
            "fit_iter": 8, 
            "chi2": 0.5716313160351515, 
            "N": 498.8745778389562, 
            "tau": 261.32427147881515, 
            "M": 106.25390307771721, 
            "mean": 1156.4639413591822, 
            "mean_err": 8.967603413419893, 
            "sig": 215.17948626640307, 
            "out_of_bounds": false, 
            "adcPerMIP": 920.8168825356528, 
            "adcPerMIP_err": 8.967603413419893
        }, 
        "bad_adcfit_reasons": [], 
        "pedestal": 235.64705882352942, 
        "thresh": 75.35294117647058, 
        "adcPerMIP": 920.810002509215, 
        "good_pefit": true, 
        "pefit_results": {
            "fit_iter": 2, 
            "chi2": 0.0011408606143612063, 
            "N": 0.9960479757313229, 
            "tau": 261.28392543798975, 
            "M": 0.2120929827240339, 
            "mean": 1156.4570613327444, 
            "mean_err": 8.974336263504169, 
            "sig": 215.21231247971997, 
            "out_of_bounds": false, 
            "adcPerMIP": 920.810002509215, 
            "adcPerMIP_err": 8.974336263504169, 
            "pePerMIP": 44.33909595894847, 
            "pePerMIP_err": 0.43213470278457394
        }, 
        "bad_pefit_reasons": [], 
        "gain": 20.7674509954319, 
        "good_gain": true, 
        "bad_gain_reasons": [], 
        "pePerMIP": 44.33909595894847
    }, 
    "002500104853500520353041": {
        "channel": "7", 
        "voltage": 2520, 
        "threshold": 1375, 
        "temperature": -36.68199999999999, 
        "temp_K": 236.468, 
        "good_adcfit": false, 
        "adcfit_results": {
            "fit_iter": 1, 
            "chi2": 2787052.0151104685, 
            "N": 112099.99999348146, 
            "tau": 66.58391740505341, 
            "M": 10.000000052706929, 
            "mean": 355.00000000000006, 
            "mean_err": 1170460.6526462673, 
            "sig": 50.00000544271613, 
            "out_of_bounds": true, 
            "adcPerMIP": 66.70588235294122, 
            "adcPerMIP_err": 1170460.6526462673
        }, 
        "bad_adcfit_reasons": [
            "opt[0] at upper bound", 
            "opt[2] at lower bound", 
            "opt[3] at lower bound", 
            "opt[4] at lower bound", 
            "large chi2 of 2787052.0"
        ], 
        "pedestal": 288.29411764705884, 
        "thresh": 60.70588235294116, 
        "adcPerMIP": 1042.1754974842675, 
        "good_pefit": true, 
        "pefit_results": {
            "fit_iter": 3, 
            "chi2": 0.0003858654140313351, 
            "N": 0.46357786559196434, 
            "tau": 295.3979861259161, 
            "M": 0.08421531713685788, 
            "mean": 1330.4696151313262, 
            "mean_err": 7.4600613357188905, 
            "sig": 230.75457466844693, 
            "out_of_bounds": false, 
            "adcPerMIP": 1042.1754974842675, 
            "adcPerMIP_err": 7.4600613357188905, 
            "pePerMIP": 45.637865095176906, 
            "pePerMIP_err": 0.32668324448534014
        }, 
        "bad_pefit_reasons": [], 
        "gain": 22.835763577258273, 
        "good_gain": true, 
        "bad_gain_reasons": [], 
        "pePerMIP": 45.637865095176906
    }, 
    "0025001c4853500520353041": {
        "channel": "8", 
        "voltage": 2520, 
        "threshold": 1368, 
        "temperature": -36.36899999999997, 
        "temp_K": 236.781, 
        "good_adcfit": true, 
        "adcfit_results": {
            "fit_iter": 6, 
            "chi2": 1.3843614786510723, 
            "N": 1379.5156256560153, 
            "tau": 192.4023325898198, 
            "M": 122.45653401191157, 
            "mean": 1099.66434367561, 
            "mean_err": 13.320841271610334, 
            "sig": 210.87185371711004, 
            "out_of_bounds": false, 
            "adcPerMIP": 839.1389199467965, 
            "adcPerMIP_err": 13.320841271610334
        }, 
        "bad_adcfit_reasons": [], 
        "pedestal": 260.52542372881356, 
        "thresh": 53.474576271186436, 
        "adcPerMIP": 877.5188679388671, 
        "good_pefit": true, 
        "pefit_results": {
            "fit_iter": 12, 
            "chi2": 0.0009058099499593741, 
            "N": 0.5992816394830813, 
            "tau": 239.34432594820876, 
            "M": 0.08560990828540475, 
            "mean": 1138.0442916676807, 
            "mean_err": 11.590628963989078, 
            "sig": 202.7578008405597, 
            "out_of_bounds": false, 
            "adcPerMIP": 877.5188679388671, 
            "adcPerMIP_err": 11.590628963989078, 
            "pePerMIP": 44.05829049524193, 
            "pePerMIP_err": 0.5819399634305885
        }, 
        "bad_pefit_reasons": [], 
        "gain": 19.91722461482328, 
        "good_gain": true, 
        "bad_gain_reasons": [], 
        "pePerMIP": 44.05829049524193
    }
}