{
    "runNum": "0002198", 
    "0025001b4853500520353041": {
        "channel": "1", 
        "voltage": 2460, 
        "threshold": 1344, 
        "temperature": -37.74799999999999, 
        "temp_K": 235.402, 
        "good_adcfit": true, 
        "adcfit_results": {
            "fit_iter": 6, 
            "chi2": 0.5451933692588361, 
            "N": 807.4579623356033, 
            "tau": 177.43564021059, 
            "M": 209.36118594244687, 
            "mean": 795.9379904700533, 
            "mean_err": 3.523165962901272, 
            "sig": 129.3207577265684, 
            "out_of_bounds": false, 
            "adcPerMIP": 582.0808476129104, 
            "adcPerMIP_err": 3.523165962901272
        }, 
        "bad_adcfit_reasons": [], 
        "pedestal": 213.85714285714286, 
        "thresh": 57.14285714285714, 
        "adcPerMIP": 582.5229420360458, 
        "good_pefit": true, 
        "pefit_results": {
            "fit_iter": 2, 
            "chi2": 0.0011323548579127785, 
            "N": 1.6742165581932584, 
            "tau": 178.50531613233608, 
            "M": 0.43963446841180215, 
            "mean": 796.3800848931887, 
            "mean_err": 3.585247575242646, 
            "sig": 129.53038343177587, 
            "out_of_bounds": false, 
            "adcPerMIP": 582.5229420360458, 
            "adcPerMIP_err": 3.585247575242646, 
            "pePerMIP": 37.307429589990534, 
            "pePerMIP_err": 0.22961562854252807
        }, 
        "bad_pefit_reasons": [], 
        "gain": 15.614126956426258, 
        "good_gain": true, 
        "bad_gain_reasons": [], 
        "pePerMIP": 37.307429589990534
    }, 
    "0033000b4853500720353041": {
        "channel": "2", 
        "voltage": 2460, 
        "threshold": 1350, 
        "temperature": -36.86899999999997, 
        "temp_K": 236.281, 
        "good_adcfit": true, 
        "adcfit_results": {
            "fit_iter": 3, 
            "chi2": 0.8505151082917348, 
            "N": 591.345202170771, 
            "tau": 222.2786304327785, 
            "M": 158.7764734483883, 
            "mean": 923.9638175913766, 
            "mean_err": 5.471419605799808, 
            "sig": 148.80832983548126, 
            "out_of_bounds": false, 
            "adcPerMIP": 677.3282243710375, 
            "adcPerMIP_err": 5.471419605799808
        }, 
        "bad_adcfit_reasons": [], 
        "pedestal": 246.635593220339, 
        "thresh": 43.36440677966101, 
        "adcPerMIP": 678.2820877125368, 
        "good_pefit": true, 
        "pefit_results": {
            "fit_iter": 2, 
            "chi2": 0.0007817884828750731, 
            "N": 0.5259106062116974, 
            "tau": 225.71050637868015, 
            "M": 0.14507469744410073, 
            "mean": 924.9176809328759, 
            "mean_err": 5.4617722256670795, 
            "sig": 148.6920273070407, 
            "out_of_bounds": false, 
            "adcPerMIP": 678.2820877125368, 
            "adcPerMIP_err": 5.4617722256670795, 
            "pePerMIP": 40.69199814927718, 
            "pePerMIP_err": 0.32766665864366806
        }, 
        "bad_pefit_reasons": [], 
        "gain": 16.66868471841276, 
        "good_gain": true, 
        "bad_gain_reasons": [], 
        "pePerMIP": 40.69199814927718
    }, 
    "0025000f4853500520353041": {
        "channel": "3", 
        "voltage": 2460, 
        "threshold": 1344, 
        "temperature": -36.74399999999997, 
        "temp_K": 236.406, 
        "good_adcfit": true, 
        "adcfit_results": {
            "fit_iter": 6, 
            "chi2": 0.9441581856798142, 
            "N": 692.718276595644, 
            "tau": 199.88912283480667, 
            "M": 162.5003260764511, 
            "mean": 895.499930414782, 
            "mean_err": 5.1601326853399225, 
            "sig": 148.11561704741985, 
            "out_of_bounds": false, 
            "adcPerMIP": 670.4411068853703, 
            "adcPerMIP_err": 5.1601326853399225
        }, 
        "bad_adcfit_reasons": [], 
        "pedestal": 225.05882352941177, 
        "thresh": 60.94117647058823, 
        "adcPerMIP": 664.5019099414003, 
        "good_pefit": true, 
        "pefit_results": {
            "fit_iter": 2, 
            "chi2": 0.0022363538424262103, 
            "N": 2.058914766801232, 
            "tau": 183.53806215009038, 
            "M": 0.4038236150018458, 
            "mean": 889.5607334708121, 
            "mean_err": 5.281547863155662, 
            "sig": 149.4860056701702, 
            "out_of_bounds": false, 
            "adcPerMIP": 664.5019099414003, 
            "adcPerMIP_err": 5.281547863155662, 
            "pePerMIP": 39.23543778621367, 
            "pePerMIP_err": 0.31184837770899404
        }, 
        "bad_pefit_reasons": [], 
        "gain": 16.936268522404234, 
        "good_gain": true, 
        "bad_gain_reasons": [], 
        "pePerMIP": 39.23543778621367
    }, 
    "002100384853500520353041": {
        "channel": "4", 
        "voltage": 2460, 
        "threshold": 1346, 
        "temperature": -36.93199999999999, 
        "temp_K": 236.218, 
        "good_adcfit": true, 
        "adcfit_results": {
            "fit_iter": 2, 
            "chi2": 0.810642325183911, 
            "N": 1641.1987855078437, 
            "tau": 158.28707689881273, 
            "M": 194.74390542674973, 
            "mean": 802.6734790691628, 
            "mean_err": 4.4593267042261155, 
            "sig": 118.93866789390529, 
            "out_of_bounds": false, 
            "adcPerMIP": 524.1151457358294, 
            "adcPerMIP_err": 4.4593267042261155
        }, 
        "bad_adcfit_reasons": [], 
        "pedestal": 278.55833333333334, 
        "thresh": 36.44166666666666, 
        "adcPerMIP": 527.035088313612, 
        "good_pefit": true, 
        "pefit_results": {
            "fit_iter": 2, 
            "chi2": 0.0007740121064238307, 
            "N": 1.3729881662975016, 
            "tau": 166.3608100211877, 
            "M": 0.1844834516837936, 
            "mean": 805.5934216469453, 
            "mean_err": 4.385660259561605, 
            "sig": 118.38724747372444, 
            "out_of_bounds": false, 
            "adcPerMIP": 527.035088313612, 
            "adcPerMIP_err": 4.385660259561605, 
            "pePerMIP": 37.08397662530006, 
            "pePerMIP_err": 0.30858993292551407
        }, 
        "bad_pefit_reasons": [], 
        "gain": 14.211935619494735, 
        "good_gain": true, 
        "bad_gain_reasons": [], 
        "pePerMIP": 37.08397662530006
    }, 
    "0025000c4853500520353041": {
        "channel": "5", 
        "voltage": 2460, 
        "threshold": 1346, 
        "temperature": -36.86899999999997, 
        "temp_K": 236.281, 
        "good_adcfit": false, 
        "adcfit_results": {
            "fit_iter": 1, 
            "chi2": 71483.00283896625, 
            "N": 60799.99999999838, 
            "tau": 61.66180936799546, 
            "M": 10.000000000000002, 
            "mean": 306.00000000000006, 
            "mean_err": 1256647.5021399758, 
            "sig": 50.00000000000001, 
            "out_of_bounds": true, 
            "adcPerMIP": 54.75833333333338, 
            "adcPerMIP_err": 1256647.5021399758
        }, 
        "bad_adcfit_reasons": [
            "opt[0] at upper bound", 
            "opt[2] at lower bound", 
            "opt[3] at lower bound", 
            "opt[4] at lower bound", 
            "large chi2 of 71483.0"
        ], 
        "pedestal": 251.24166666666667, 
        "thresh": 47.758333333333326, 
        "adcPerMIP": 476.4837070064639, 
        "good_pefit": true, 
        "pefit_results": {
            "fit_iter": 2, 
            "chi2": 0.0013445983107539393, 
            "N": 3.064777933215239, 
            "tau": 143.04660512562614, 
            "M": 0.3383891807670816, 
            "mean": 727.7253736731305, 
            "mean_err": 4.768740779180234, 
            "sig": 113.3864750173924, 
            "out_of_bounds": false, 
            "adcPerMIP": 476.4837070064639, 
            "adcPerMIP_err": 4.768740779180234, 
            "pePerMIP": 34.30016377923539, 
            "pePerMIP_err": 0.34328265025939636
        }, 
        "bad_pefit_reasons": [], 
        "gain": 13.891586934489137, 
        "good_gain": true, 
        "bad_gain_reasons": [], 
        "pePerMIP": 34.30016377923539
    }, 
    "002400084853500520353041": {
        "channel": "6", 
        "voltage": 2460, 
        "threshold": 1346, 
        "temperature": -36.36899999999997, 
        "temp_K": 236.781, 
        "good_adcfit": true, 
        "adcfit_results": {
            "fit_iter": 5, 
            "chi2": 0.8222603980372312, 
            "N": 1818.8795229695393, 
            "tau": 144.63450541779437, 
            "M": 189.65844693497723, 
            "mean": 759.7713811042721, 
            "mean_err": 5.4007908870336445, 
            "sig": 126.09387651192387, 
            "out_of_bounds": false, 
            "adcPerMIP": 524.1389024717935, 
            "adcPerMIP_err": 5.4007908870336445
        }, 
        "bad_adcfit_reasons": [], 
        "pedestal": 235.63247863247864, 
        "thresh": 53.36752136752136, 
        "adcPerMIP": 529.6333312091822, 
        "good_pefit": true, 
        "pefit_results": {
            "fit_iter": 2, 
            "chi2": 0.0016407408402646408, 
            "N": 2.9936140773414177, 
            "tau": 154.7568210404082, 
            "M": 0.3669537220419801, 
            "mean": 765.2658098416608, 
            "mean_err": 5.300470868245056, 
            "sig": 125.09951145579153, 
            "out_of_bounds": false, 
            "adcPerMIP": 529.6333312091822, 
            "adcPerMIP_err": 5.300470868245056, 
            "pePerMIP": 35.712668041048644, 
            "pePerMIP_err": 0.35740567185738864
        }, 
        "bad_pefit_reasons": [], 
        "gain": 14.830405014837147, 
        "good_gain": true, 
        "bad_gain_reasons": [], 
        "pePerMIP": 35.712668041048644
    }, 
    "002500104853500520353041": {
        "channel": "7", 
        "voltage": 2460, 
        "threshold": 1357, 
        "temperature": -36.68199999999999, 
        "temp_K": 236.468, 
        "good_adcfit": true, 
        "adcfit_results": {
            "fit_iter": 3, 
            "chi2": 0.46854910872616995, 
            "N": 1440.2019037604307, 
            "tau": 184.24882410287955, 
            "M": 149.51701611347593, 
            "mean": 945.0568175141747, 
            "mean_err": 4.718039291652633, 
            "sig": 151.22627505475444, 
            "out_of_bounds": false, 
            "adcPerMIP": 656.1257830314161, 
            "adcPerMIP_err": 4.718039291652633
        }, 
        "bad_adcfit_reasons": [], 
        "pedestal": 288.9310344827586, 
        "thresh": 43.068965517241395, 
        "adcPerMIP": 653.7077360166801, 
        "good_pefit": true, 
        "pefit_results": {
            "fit_iter": 2, 
            "chi2": 0.0004110585773523951, 
            "N": 1.3478167205413232, 
            "tau": 179.97344781234983, 
            "M": 0.1320739883363686, 
            "mean": 942.6387704994387, 
            "mean_err": 4.752656532469434, 
            "sig": 151.55293596789468, 
            "out_of_bounds": false, 
            "adcPerMIP": 653.7077360166801, 
            "adcPerMIP_err": 4.752656532469434, 
            "pePerMIP": 38.116758122283606, 
            "pePerMIP_err": 0.2771205685744036
        }, 
        "bad_pefit_reasons": [], 
        "gain": 17.15013994420772, 
        "good_gain": true, 
        "bad_gain_reasons": [], 
        "pePerMIP": 38.116758122283606
    }, 
    "0025001c4853500520353041": {
        "channel": "8", 
        "voltage": 2460, 
        "threshold": 1350, 
        "temperature": -36.43199999999999, 
        "temp_K": 236.718, 
        "good_adcfit": true, 
        "adcfit_results": {
            "fit_iter": 3, 
            "chi2": 1.0604960712409361, 
            "N": 2865.7216712081636, 
            "tau": 137.41844610022008, 
            "M": 199.4384501282013, 
            "mean": 747.0703429251256, 
            "mean_err": 5.658094465198012, 
            "sig": 113.37159126982002, 
            "out_of_bounds": false, 
            "adcPerMIP": 486.180512416651, 
            "adcPerMIP_err": 5.658094465198012
        }, 
        "bad_adcfit_reasons": [], 
        "pedestal": 260.8898305084746, 
        "thresh": 23.110169491525426, 
        "adcPerMIP": 487.78397564772274, 
        "good_pefit": true, 
        "pefit_results": {
            "fit_iter": 3, 
            "chi2": 0.000813142668787508, 
            "N": 2.051513472034138, 
            "tau": 140.43488025093944, 
            "M": 0.15122307153477116, 
            "mean": 748.6738061561973, 
            "mean_err": 5.509692849927246, 
            "sig": 112.50134337197923, 
            "out_of_bounds": false, 
            "adcPerMIP": 487.78397564772274, 
            "adcPerMIP_err": 5.509692849927246, 
            "pePerMIP": 35.3896830687916, 
            "pePerMIP_err": 0.3997390105043782
        }, 
        "bad_pefit_reasons": [], 
        "gain": 13.783225317377175, 
        "good_gain": true, 
        "bad_gain_reasons": [], 
        "pePerMIP": 35.3896830687916
    }
}