{
    "runNum": "0002342", 
    "0025001b4853500520353041": {
        "channel": "1", 
        "voltage": 2680, 
        "threshold": 1410, 
        "temperature": -3.4939999999999714, 
        "temp_K": 269.656, 
        "good_adcfit": false, 
        "adcfit_results": {
            "fit_iter": 21, 
            "chi2": 1040.799170873512, 
            "N": 26499.99999998314, 
            "tau": 69.48698915121165, 
            "M": 175.41530657406858, 
            "mean": 479.40413680612073, 
            "mean_err": 2137.8378181832118, 
            "sig": 126.1771261203574, 
            "out_of_bounds": true, 
            "adcPerMIP": 259.1345715887294, 
            "adcPerMIP_err": 2137.8378181832118
        }, 
        "bad_adcfit_reasons": [
            "exceeded 20 fit iterations", 
            "opt[0] at upper bound", 
            "large chi2 of 1040.8"
        ], 
        "pedestal": 220.26956521739132, 
        "thresh": 125.73043478260868, 
        "adcPerMIP": 1229.7605568290865, 
        "good_pefit": true, 
        "pefit_results": {
            "fit_iter": 2, 
            "chi2": 0.001980269573141692, 
            "N": 0.9012826939846066, 
            "tau": 360.40967313295806, 
            "M": 0.3900154308834578, 
            "mean": 1450.0301220464778, 
            "mean_err": 6.8287527753526955, 
            "sig": 260.10178251457467, 
            "out_of_bounds": false, 
            "adcPerMIP": 1229.7605568290865, 
            "adcPerMIP_err": 6.8287527753526955, 
            "pePerMIP": 48.56862438512873, 
            "pePerMIP_err": 0.2696973217454602
        }, 
        "bad_pefit_reasons": [], 
        "gain": 25.320061508796364, 
        "good_gain": true, 
        "bad_gain_reasons": [], 
        "pePerMIP": 48.56862438512873
    }, 
    "0033000b4853500720353041": {
        "channel": "2", 
        "voltage": 2680, 
        "threshold": 1416, 
        "temperature": -3.2439999999999714, 
        "temp_K": 269.906, 
        "good_adcfit": false, 
        "adcfit_results": {
            "fit_iter": 12, 
            "chi2": 589.4504817006263, 
            "N": 37899.99999882107, 
            "tau": 70.76704393285799, 
            "M": 188.49330635551888, 
            "mean": 474.6484368064027, 
            "mean_err": 3391.565466713624, 
            "sig": 143.42259551269257, 
            "out_of_bounds": true, 
            "adcPerMIP": 222.47299820991145, 
            "adcPerMIP_err": 3391.565466713624
        }, 
        "bad_adcfit_reasons": [
            "opt[0] at upper bound", 
            "large chi2 of 589.5"
        ], 
        "pedestal": 252.17543859649123, 
        "thresh": 101.82456140350877, 
        "adcPerMIP": 1374.5420698149653, 
        "good_pefit": true, 
        "pefit_results": {
            "fit_iter": 3, 
            "chi2": 0.0011800712170803673, 
            "N": 0.5889845768903915, 
            "tau": 396.2699451953512, 
            "M": 0.21887246467772328, 
            "mean": 1626.7175084114565, 
            "mean_err": 9.116034512755254, 
            "sig": 304.30555030396135, 
            "out_of_bounds": false, 
            "adcPerMIP": 1374.5420698149653, 
            "adcPerMIP_err": 9.116034512755254, 
            "pePerMIP": 51.250225818044456, 
            "pePerMIP_err": 0.33989416373897224
        }, 
        "bad_pefit_reasons": [], 
        "gain": 26.820214894175336, 
        "good_gain": true, 
        "bad_gain_reasons": [], 
        "pePerMIP": 51.250225818044456
    }, 
    "0025000f4853500520353041": {
        "channel": "3", 
        "voltage": 2680, 
        "threshold": 1410, 
        "temperature": -3.6189999999999714, 
        "temp_K": 269.531, 
        "good_adcfit": false, 
        "adcfit_results": {
            "fit_iter": 21, 
            "chi2": 1023.2293651664597, 
            "N": 22850.17047153098, 
            "tau": 70.33306964443227, 
            "M": 233.16646674157013, 
            "mean": 387.00013551386314, 
            "mean_err": 12858.052017274418, 
            "sig": 143.05105080179308, 
            "out_of_bounds": true, 
            "adcPerMIP": 161.0966267419333, 
            "adcPerMIP_err": 12858.052017274418
        }, 
        "bad_adcfit_reasons": [
            "exceeded 20 fit iterations", 
            "opt[3] at lower bound", 
            "large chi2 of 1023.2"
        ], 
        "pedestal": 225.90350877192984, 
        "thresh": 155.09649122807016, 
        "adcPerMIP": 1420.2825384467992, 
        "good_pefit": true, 
        "pefit_results": {
            "fit_iter": 3, 
            "chi2": 0.0020026557034230267, 
            "N": 0.7770213014363045, 
            "tau": 406.2609396448508, 
            "M": 0.3081105031384604, 
            "mean": 1646.186047218729, 
            "mean_err": 8.575302793913346, 
            "sig": 303.4212297044554, 
            "out_of_bounds": false, 
            "adcPerMIP": 1420.2825384467992, 
            "adcPerMIP_err": 8.575302793913346, 
            "pePerMIP": 51.58173565032565, 
            "pePerMIP_err": 0.3114373301532397
        }, 
        "bad_pefit_reasons": [], 
        "gain": 27.53460155111769, 
        "good_gain": true, 
        "bad_gain_reasons": [], 
        "pePerMIP": 51.58173565032565
    }, 
    "002100384853500520353041": {
        "channel": "4", 
        "voltage": 2680, 
        "threshold": 1412, 
        "temperature": -4.118999999999971, 
        "temp_K": 269.031, 
        "good_adcfit": false, 
        "adcfit_results": {
            "fit_iter": 21, 
            "chi2": 159.87553128457492, 
            "N": 39055.76080641824, 
            "tau": 73.64638647977752, 
            "M": 233.9269515615151, 
            "mean": 410.0000006846234, 
            "mean_err": 16588.91946523505, 
            "sig": 161.68056543895025, 
            "out_of_bounds": true, 
            "adcPerMIP": 124.31531599993872, 
            "adcPerMIP_err": 16588.91946523505
        }, 
        "bad_adcfit_reasons": [
            "exceeded 20 fit iterations", 
            "opt[3] at lower bound", 
            "large chi2 of 159.9"
        ], 
        "pedestal": 285.68468468468467, 
        "thresh": 116.31531531531533, 
        "adcPerMIP": 1242.1589838602995, 
        "good_pefit": true, 
        "pefit_results": {
            "fit_iter": 2, 
            "chi2": 0.001535987853487019, 
            "N": 0.7822901352399991, 
            "tau": 344.73585158279593, 
            "M": 0.21150380493524404, 
            "mean": 1527.8436685449842, 
            "mean_err": 10.88129368892775, 
            "sig": 283.8052366547462, 
            "out_of_bounds": false, 
            "adcPerMIP": 1242.1589838602995, 
            "adcPerMIP_err": 10.88129368892775, 
            "pePerMIP": 49.76634050333966, 
            "pePerMIP_err": 0.43595238119770513
        }, 
        "bad_pefit_reasons": [], 
        "gain": 24.95982166454337, 
        "good_gain": true, 
        "bad_gain_reasons": [], 
        "pePerMIP": 49.76634050333966
    }, 
    "0025000c4853500520353041": {
        "channel": "5", 
        "voltage": 2680, 
        "threshold": 1412, 
        "temperature": -4.243999999999971, 
        "temp_K": 268.906, 
        "good_adcfit": false, 
        "adcfit_results": {
            "fit_iter": 10, 
            "chi2": 717.5521229456781, 
            "N": 32099.999999999683, 
            "tau": 74.49179019453095, 
            "M": 188.063713601457, 
            "mean": 520.7255466462256, 
            "mean_err": 1066.6196265865258, 
            "sig": 128.3631018790384, 
            "out_of_bounds": true, 
            "adcPerMIP": 264.9570281277071, 
            "adcPerMIP_err": 1066.6196265865258
        }, 
        "bad_adcfit_reasons": [
            "opt[0] at upper bound", 
            "large chi2 of 717.6"
        ], 
        "pedestal": 255.7685185185185, 
        "thresh": 119.2314814814815, 
        "adcPerMIP": 1288.475025834326, 
        "good_pefit": true, 
        "pefit_results": {
            "fit_iter": 2, 
            "chi2": 0.0010388734581737505, 
            "N": 0.8434468314346331, 
            "tau": 372.6119825747434, 
            "M": 0.2453600150875602, 
            "mean": 1544.2435443528445, 
            "mean_err": 10.8598576717822, 
            "sig": 301.69250692591976, 
            "out_of_bounds": false, 
            "adcPerMIP": 1288.475025834326, 
            "adcPerMIP_err": 10.8598576717822, 
            "pePerMIP": 49.78086147114989, 
            "pePerMIP_err": 0.41957590136862055
        }, 
        "bad_pefit_reasons": [], 
        "gain": 25.8829395023839, 
        "good_gain": true, 
        "bad_gain_reasons": [], 
        "pePerMIP": 49.78086147114989
    }, 
    "002400084853500520353041": {
        "channel": "6", 
        "voltage": 2680, 
        "threshold": 1412, 
        "temperature": -3.9939999999999714, 
        "temp_K": 269.156, 
        "good_adcfit": false, 
        "adcfit_results": {
            "fit_iter": 5, 
            "chi2": 399.70752282537956, 
            "N": 33999.99999999304, 
            "tau": 75.33910357189849, 
            "M": 180.8141770136147, 
            "mean": 552.0349634894967, 
            "mean_err": 867.3446235344272, 
            "sig": 143.8208836999473, 
            "out_of_bounds": true, 
            "adcPerMIP": 302.19337933108085, 
            "adcPerMIP_err": 867.3446235344272
        }, 
        "bad_adcfit_reasons": [
            "opt[0] at upper bound", 
            "large chi2 of 399.7"
        ], 
        "pedestal": 249.84158415841586, 
        "thresh": 123.15841584158414, 
        "adcPerMIP": 1275.8350649301003, 
        "good_pefit": true, 
        "pefit_results": {
            "fit_iter": 3, 
            "chi2": 0.0011592124303854165, 
            "N": 1.1227822312981932, 
            "tau": 319.9654632584407, 
            "M": 0.2469515312119615, 
            "mean": 1525.6766490885161, 
            "mean_err": 9.956242946685405, 
            "sig": 300.80087683536703, 
            "out_of_bounds": false, 
            "adcPerMIP": 1275.8350649301003, 
            "adcPerMIP_err": 9.956242946685405, 
            "pePerMIP": 48.32034471366304, 
            "pePerMIP_err": 0.3770778092410971
        }, 
        "bad_pefit_reasons": [], 
        "gain": 26.403683013655026, 
        "good_gain": true, 
        "bad_gain_reasons": [], 
        "pePerMIP": 48.32034471366304
    }, 
    "002500104853500520353041": {
        "channel": "7", 
        "voltage": 2680, 
        "threshold": 1423, 
        "temperature": -4.4319999999999595, 
        "temp_K": 268.718, 
        "good_adcfit": false, 
        "adcfit_results": {
            "fit_iter": 4, 
            "chi2": 147.75347227383327, 
            "N": 49299.99999999999, 
            "tau": 81.76362785265128, 
            "M": 174.38317135082735, 
            "mean": 657.8544761461462, 
            "mean_err": 320.5117717692108, 
            "sig": 149.30103199301124, 
            "out_of_bounds": true, 
            "adcPerMIP": 355.98410577577584, 
            "adcPerMIP_err": 320.5117717692108
        }, 
        "bad_adcfit_reasons": [
            "opt[0] at upper bound", 
            "large chi2 of 147.8"
        ], 
        "pedestal": 301.8703703703704, 
        "thresh": 102.12962962962962, 
        "adcPerMIP": 1360.1928949104888, 
        "good_pefit": true, 
        "pefit_results": {
            "fit_iter": 2, 
            "chi2": 0.0007329797255477846, 
            "N": 0.695293323639813, 
            "tau": 380.006678281725, 
            "M": 0.15479440655432875, 
            "mean": 1662.0632652808592, 
            "mean_err": 9.265551916805514, 
            "sig": 295.8099467825777, 
            "out_of_bounds": false, 
            "adcPerMIP": 1360.1928949104888, 
            "adcPerMIP_err": 9.265551916805514, 
            "pePerMIP": 49.43555734216899, 
            "pePerMIP_err": 0.33675203333584963
        }, 
        "bad_pefit_reasons": [], 
        "gain": 27.514464649318956, 
        "good_gain": true, 
        "bad_gain_reasons": [], 
        "pePerMIP": 49.43555734216899
    }, 
    "0025001c4853500520353041": {
        "channel": "8", 
        "voltage": 2680, 
        "threshold": 1416, 
        "temperature": -4.118999999999971, 
        "temp_K": 269.031, 
        "good_adcfit": false, 
        "adcfit_results": {
            "fit_iter": 4, 
            "chi2": 406.306720441036, 
            "N": 53799.999999999985, 
            "tau": 72.08909104771672, 
            "M": 243.61193976194164, 
            "mean": 543.2709383429781, 
            "mean_err": 628.0399650697087, 
            "sig": 116.76896143410117, 
            "out_of_bounds": true, 
            "adcPerMIP": 279.55542110159877, 
            "adcPerMIP_err": 628.0399650697087
        }, 
        "bad_adcfit_reasons": [
            "opt[0] at upper bound", 
            "large chi2 of 406.3"
        ], 
        "pedestal": 263.7155172413793, 
        "thresh": 118.2844827586207, 
        "adcPerMIP": 1281.6384556539108, 
        "good_pefit": true, 
        "pefit_results": {
            "fit_iter": 3, 
            "chi2": 0.0013010382141346425, 
            "N": 0.5667414088301362, 
            "tau": 396.3736170399282, 
            "M": 0.13977112266672398, 
            "mean": 1545.35397289529, 
            "mean_err": 11.002047271402411, 
            "sig": 269.9900038402628, 
            "out_of_bounds": false, 
            "adcPerMIP": 1281.6384556539108, 
            "adcPerMIP_err": 11.002047271402411, 
            "pePerMIP": 50.60215091577721, 
            "pePerMIP_err": 0.434387134650988
        }, 
        "bad_pefit_reasons": [], 
        "gain": 25.327746596920047, 
        "good_gain": true, 
        "bad_gain_reasons": [], 
        "pePerMIP": 50.60215091577721
    }
}