{
    "runNum": "0002163", 
    "0025001b4853500520353041": {
        "channel": "1", 
        "voltage": 2520, 
        "threshold": 1362, 
        "temperature": -41.86899999999997, 
        "temp_K": 231.281, 
        "good_adcfit": false, 
        "adcfit_results": {
            "fit_iter": 4, 
            "chi2": 758.698483777543, 
            "N": 57499.99999999999, 
            "tau": 58.92551024734798, 
            "M": 224.22117535992973, 
            "mean": 451.3824215102156, 
            "mean_err": 439.41082658555524, 
            "sig": 102.02040915855176, 
            "out_of_bounds": true, 
            "adcPerMIP": 238.7907548435489, 
            "adcPerMIP_err": 439.41082658555524
        }, 
        "bad_adcfit_reasons": [
            "opt[0] at upper bound", 
            "large chi2 of 758.7"
        ], 
        "pedestal": 212.59166666666667, 
        "thresh": 83.40833333333333, 
        "adcPerMIP": 1075.6062469547905, 
        "good_pefit": true, 
        "pefit_results": {
            "fit_iter": 2, 
            "chi2": 0.0009438353046118926, 
            "N": 0.5358484522707023, 
            "tau": 315.80859768401547, 
            "M": 0.19595647803721858, 
            "mean": 1288.1979136214572, 
            "mean_err": 6.7354346118403114, 
            "sig": 231.0531821037689, 
            "out_of_bounds": false, 
            "adcPerMIP": 1075.6062469547905, 
            "adcPerMIP_err": 6.7354346118403114, 
            "pePerMIP": 46.84572427094642, 
            "pePerMIP_err": 0.2933474155292093
        }, 
        "bad_pefit_reasons": [], 
        "gain": 22.960606623001418, 
        "good_gain": true, 
        "bad_gain_reasons": [], 
        "pePerMIP": 46.84572427094642
    }, 
    "0033000b4853500720353041": {
        "channel": "2", 
        "voltage": 2520, 
        "threshold": 1368, 
        "temperature": -40.86899999999997, 
        "temp_K": 232.281, 
        "good_adcfit": false, 
        "adcfit_results": {
            "fit_iter": 1, 
            "chi2": 9098835.406521615, 
            "N": 118299.99997016463, 
            "tau": 58.86521136750166, 
            "M": 10.000000049894597, 
            "mean": 316.00000000000006, 
            "mean_err": 1363301.0583200778, 
            "sig": 50.00000531407082, 
            "out_of_bounds": true, 
            "adcPerMIP": 68.9173553719009, 
            "adcPerMIP_err": 1363301.0583200778
        }, 
        "bad_adcfit_reasons": [
            "opt[0] at upper bound", 
            "opt[2] at lower bound", 
            "opt[3] at lower bound", 
            "opt[4] at lower bound", 
            "large chi2 of 9098835.4"
        ], 
        "pedestal": 247.08264462809916, 
        "thresh": 63.91735537190084, 
        "adcPerMIP": 1156.6011407156457, 
        "good_pefit": true, 
        "pefit_results": {
            "fit_iter": 6, 
            "chi2": 0.000590432775191414, 
            "N": 0.30372297413017263, 
            "tau": 310.8745409960351, 
            "M": 0.08043909800050003, 
            "mean": 1403.6837853437448, 
            "mean_err": 10.59329814335525, 
            "sig": 268.89435335975327, 
            "out_of_bounds": false, 
            "adcPerMIP": 1156.6011407156457, 
            "adcPerMIP_err": 10.59329814335525, 
            "pePerMIP": 48.61248219567245, 
            "pePerMIP_err": 0.4452412324863108
        }, 
        "bad_pefit_reasons": [], 
        "gain": 23.792266686982874, 
        "good_gain": true, 
        "bad_gain_reasons": [], 
        "pePerMIP": 48.61248219567245
    }, 
    "0025000f4853500520353041": {
        "channel": "3", 
        "voltage": 2520, 
        "threshold": 1362, 
        "temperature": -40.56099999999998, 
        "temp_K": 232.589, 
        "good_adcfit": false, 
        "adcfit_results": {
            "fit_iter": 3, 
            "chi2": 1294.339947866313, 
            "N": 60099.99999999999, 
            "tau": 60.60781393975055, 
            "M": 233.20007648193828, 
            "mean": 461.8029965041048, 
            "mean_err": 468.15721480138785, 
            "sig": 96.27713304059154, 
            "out_of_bounds": true, 
            "adcPerMIP": 236.58632983743811, 
            "adcPerMIP_err": 468.15721480138785
        }, 
        "bad_adcfit_reasons": [
            "opt[0] at upper bound", 
            "large chi2 of 1294.3"
        ], 
        "pedestal": 225.21666666666667, 
        "thresh": 87.78333333333333, 
        "adcPerMIP": 1178.527732434468, 
        "good_pefit": true, 
        "pefit_results": {
            "fit_iter": 4, 
            "chi2": 0.0009453897489297721, 
            "N": 0.5628751277302574, 
            "tau": 310.70528471419516, 
            "M": 0.1543528689280665, 
            "mean": 1403.7443991011346, 
            "mean_err": 9.489847296205587, 
            "sig": 269.60478669702945, 
            "out_of_bounds": false, 
            "adcPerMIP": 1178.527732434468, 
            "adcPerMIP_err": 9.489847296205587, 
            "pePerMIP": 48.55087322192559, 
            "pePerMIP_err": 0.3909457200652937
        }, 
        "bad_pefit_reasons": [], 
        "gain": 24.27407900672411, 
        "good_gain": true, 
        "bad_gain_reasons": [], 
        "pePerMIP": 48.55087322192559
    }, 
    "002100384853500520353041": {
        "channel": "4", 
        "voltage": 2520, 
        "threshold": 1364, 
        "temperature": -40.62299999999999, 
        "temp_K": 232.527, 
        "good_adcfit": true, 
        "adcfit_results": {
            "fit_iter": 4, 
            "chi2": 0.9471022405293262, 
            "N": 453.30654681272586, 
            "tau": 284.9075040327236, 
            "M": 106.42250935388618, 
            "mean": 1260.2298506047885, 
            "mean_err": 9.086316463403623, 
            "sig": 216.29269622122925, 
            "out_of_bounds": false, 
            "adcPerMIP": 982.7587762246231, 
            "adcPerMIP_err": 9.086316463403623
        }, 
        "bad_adcfit_reasons": [], 
        "pedestal": 277.4710743801653, 
        "thresh": 57.528925619834695, 
        "adcPerMIP": 991.1803753619973, 
        "good_pefit": true, 
        "pefit_results": {
            "fit_iter": 2, 
            "chi2": 0.000909252799813388, 
            "N": 0.36847182795630373, 
            "tau": 308.66001599038725, 
            "M": 0.09920529931292238, 
            "mean": 1268.6514497421626, 
            "mean_err": 8.815559983536897, 
            "sig": 213.85995865882307, 
            "out_of_bounds": false, 
            "adcPerMIP": 991.1803753619973, 
            "adcPerMIP_err": 8.815559983536897, 
            "pePerMIP": 46.99354309051564, 
            "pePerMIP_err": 0.41796065403541294
        }, 
        "bad_pefit_reasons": [], 
        "gain": 21.09184177606817, 
        "good_gain": true, 
        "bad_gain_reasons": [], 
        "pePerMIP": 46.99354309051564
    }, 
    "0025000c4853500520353041": {
        "channel": "5", 
        "voltage": 2520, 
        "threshold": 1364, 
        "temperature": -40.43599999999998, 
        "temp_K": 232.714, 
        "good_adcfit": false, 
        "adcfit_results": {
            "fit_iter": 4, 
            "chi2": 149.98441912599296, 
            "N": 64999.99999999999, 
            "tau": 64.13058441857333, 
            "M": 197.61905806398764, 
            "mean": 520.7058062864796, 
            "mean_err": 265.10122606899307, 
            "sig": 115.8553630668964, 
            "out_of_bounds": true, 
            "adcPerMIP": 269.92132352785893, 
            "adcPerMIP_err": 265.10122606899307
        }, 
        "bad_adcfit_reasons": [
            "opt[0] at upper bound", 
            "large chi2 of 150.0"
        ], 
        "pedestal": 250.7844827586207, 
        "thresh": 60.2155172413793, 
        "adcPerMIP": 947.9071010088044, 
        "good_pefit": true, 
        "pefit_results": {
            "fit_iter": 2, 
            "chi2": 0.000948279949099365, 
            "N": 0.8980083240592336, 
            "tau": 247.75856893421818, 
            "M": 0.16492825927627183, 
            "mean": 1198.691583767425, 
            "mean_err": 9.606806228096088, 
            "sig": 225.96725648965366, 
            "out_of_bounds": false, 
            "adcPerMIP": 947.9071010088044, 
            "adcPerMIP_err": 9.606806228096088, 
            "pePerMIP": 44.715510914232986, 
            "pePerMIP_err": 0.4531807476557369
        }, 
        "bad_pefit_reasons": [], 
        "gain": 21.198619486355565, 
        "good_gain": true, 
        "bad_gain_reasons": [], 
        "pePerMIP": 44.715510914232986
    }, 
    "002400084853500520353041": {
        "channel": "6", 
        "voltage": 2520, 
        "threshold": 1364, 
        "temperature": -39.93599999999998, 
        "temp_K": 233.214, 
        "good_adcfit": false, 
        "adcfit_results": {
            "fit_iter": 12, 
            "chi2": 669.7766409899283, 
            "N": 56399.99999998186, 
            "tau": 61.245445627954126, 
            "M": 273.0953860042615, 
            "mean": 433.29113852641586, 
            "mean_err": 1371.6647142824188, 
            "sig": 93.98246252893678, 
            "out_of_bounds": true, 
            "adcPerMIP": 198.3159319148456, 
            "adcPerMIP_err": 1371.6647142824188
        }, 
        "bad_adcfit_reasons": [
            "opt[0] at upper bound", 
            "large chi2 of 669.8"
        ], 
        "pedestal": 234.97520661157026, 
        "thresh": 78.02479338842974, 
        "adcPerMIP": 1001.7340025127464, 
        "good_pefit": true, 
        "pefit_results": {
            "fit_iter": 2, 
            "chi2": 0.0009175589054779454, 
            "N": 0.7939688281878035, 
            "tau": 283.12983539583075, 
            "M": 0.17530575963813666, 
            "mean": 1236.7092091243167, 
            "mean_err": 8.64746534207102, 
            "sig": 226.78215330855554, 
            "out_of_bounds": false, 
            "adcPerMIP": 1001.7340025127464, 
            "adcPerMIP_err": 8.64746534207102, 
            "pePerMIP": 45.6695983977473, 
            "pePerMIP_err": 0.39424265158234645
        }, 
        "bad_pefit_reasons": [], 
        "gain": 21.934372923282766, 
        "good_gain": true, 
        "bad_gain_reasons": [], 
        "pePerMIP": 45.6695983977473
    }, 
    "002500104853500520353041": {
        "channel": "7", 
        "voltage": 2520, 
        "threshold": 1375, 
        "temperature": -40.12299999999999, 
        "temp_K": 233.027, 
        "good_adcfit": false, 
        "adcfit_results": {
            "fit_iter": 1, 
            "chi2": 3191156.421110045, 
            "N": 124699.9999804715, 
            "tau": 66.37930841046081, 
            "M": 10.00000000006045, 
            "mean": 356.00000000000006, 
            "mean_err": 1100264.6520115356, 
            "sig": 50.00000007226286, 
            "out_of_bounds": true, 
            "adcPerMIP": 68.35000000000008, 
            "adcPerMIP_err": 1100264.6520115356
        }, 
        "bad_adcfit_reasons": [
            "opt[0] at upper bound", 
            "opt[2] at lower bound", 
            "opt[3] at lower bound", 
            "opt[4] at lower bound", 
            "large chi2 of 3191156.4"
        ], 
        "pedestal": 287.65, 
        "thresh": 63.35000000000002, 
        "adcPerMIP": 1095.3173684946378, 
        "good_pefit": true, 
        "pefit_results": {
            "fit_iter": 4, 
            "chi2": 0.0003255481331225886, 
            "N": 0.529428659105773, 
            "tau": 271.7373831031771, 
            "M": 0.0754265874824722, 
            "mean": 1382.9673684946376, 
            "mean_err": 8.846869983047576, 
            "sig": 259.12063113671303, 
            "out_of_bounds": false, 
            "adcPerMIP": 1095.3173684946378, 
            "adcPerMIP_err": 8.846869983047576, 
            "pePerMIP": 45.693708679279524, 
            "pePerMIP_err": 0.3690677344817595
        }, 
        "bad_pefit_reasons": [], 
        "gain": 23.97085726139199, 
        "good_gain": true, 
        "bad_gain_reasons": [], 
        "pePerMIP": 45.693708679279524
    }, 
    "0025001c4853500520353041": {
        "channel": "8", 
        "voltage": 2520, 
        "threshold": 1368, 
        "temperature": -39.99799999999999, 
        "temp_K": 233.152, 
        "good_adcfit": false, 
        "adcfit_results": {
            "fit_iter": 1, 
            "chi2": 1231726.487755798, 
            "N": 138699.99984408938, 
            "tau": 60.467072864494746, 
            "M": 10.000000012061172, 
            "mean": 321.00000000000006, 
            "mean_err": 2878824.074362449, 
            "sig": 50.000001142074474, 
            "out_of_bounds": true, 
            "adcPerMIP": 60.89166666666671, 
            "adcPerMIP_err": 2878824.074362449
        }, 
        "bad_adcfit_reasons": [
            "opt[0] at upper bound", 
            "opt[2] at lower bound", 
            "opt[3] at lower bound", 
            "opt[4] at lower bound", 
            "large chi2 of 1231726.5"
        ], 
        "pedestal": 260.10833333333335, 
        "thresh": 55.89166666666665, 
        "adcPerMIP": 977.0295901711763, 
        "good_pefit": true, 
        "pefit_results": {
            "fit_iter": 4, 
            "chi2": 0.0008575550793782585, 
            "N": 0.4105342447552029, 
            "tau": 280.23806130641816, 
            "M": 0.07132808610965206, 
            "mean": 1237.1379235045097, 
            "mean_err": 11.072393934136922, 
            "sig": 212.7267749665653, 
            "out_of_bounds": false, 
            "adcPerMIP": 977.0295901711763, 
            "adcPerMIP_err": 11.072393934136922, 
            "pePerMIP": 46.42676491033835, 
            "pePerMIP_err": 0.5261411070311273
        }, 
        "bad_pefit_reasons": [], 
        "gain": 21.044533084699395, 
        "good_gain": true, 
        "bad_gain_reasons": [], 
        "pePerMIP": 46.42676491033835
    }
}